drexel_jupyter_logger/__init__.py
drexel_jupyter_logger/activity.py
drexel_jupyter_logger/build_quiz_for_jupyterbook.py
drexel_jupyter_logger/final_tag.py
drexel_jupyter_logger/fix_kernel.py
drexel_jupyter_logger/grade_report.py
drexel_jupyter_logger/logger.py
drexel_jupyter_logger/read_log_file.py
drexel_jupyter_logger/remove_skip.py
drexel_jupyter_logger/section_toc.py
drexel_jupyter_logger/student_info_from_nb.py
drexel_jupyter_logger/tag_files.py
drexel_jupyter_logger/week_toc.py
drexel_jupyter_logger-0.0.19.dist-info/METADATA
drexel_jupyter_logger-0.0.19.dist-info/WHEEL
drexel_jupyter_logger-0.0.19.dist-info/entry_points.txt
drexel_jupyter_logger-0.0.19.dist-info/top_level.txt
drexel_jupyter_logger-0.0.19.dist-info/RECORD
