Metadata-Version: 2.1
Name: drexel-jupyter-logger
Version: 0.0.19
Summary: drexel jupyter logger package
Author: Joshua C. Agar
Requires-Dist: cryptography
